sofastats/__init__.py
sofastats/conf/__init__.py
sofastats/conf/images.py
sofastats/conf/main.py
sofastats/data_extraction/__init__.py
sofastats/data_extraction/db.py
sofastats/data_extraction/interfaces.py
sofastats/data_extraction/utils.py
sofastats/data_extraction/charts/__init__.py
sofastats/data_extraction/charts/amounts.py
sofastats/data_extraction/charts/box_plot.py
sofastats/data_extraction/charts/histogram.py
sofastats/data_extraction/charts/scatter_plot.py
sofastats/data_extraction/charts/interfaces/__init__.py
sofastats/data_extraction/charts/interfaces/amounts.py
sofastats/data_extraction/charts/interfaces/common.py
sofastats/data_extraction/charts/interfaces/xy.py
sofastats/data_extraction/stats/__init__.py
sofastats/data_extraction/stats/chi_square.py
sofastats/output/__init__.py
sofastats/output/interfaces.py
sofastats/output/utils.py
sofastats/output/charts/__init__.py
sofastats/output/charts/area.py
sofastats/output/charts/bar.py
sofastats/output/charts/box_plot.py
sofastats/output/charts/common.py
sofastats/output/charts/conf.py
sofastats/output/charts/histogram.py
sofastats/output/charts/interfaces.py
sofastats/output/charts/line.py
sofastats/output/charts/mpl_pngs.py
sofastats/output/charts/pie.py
sofastats/output/charts/scatter_plot.py
sofastats/output/charts/utils.py
sofastats/output/charts/boomslang/Bar.py
sofastats/output/charts/boomslang/ClusteredBars.py
sofastats/output/charts/boomslang/Label.py
sofastats/output/charts/boomslang/Line.py
sofastats/output/charts/boomslang/Plot.py
sofastats/output/charts/boomslang/PlotInfo.py
sofastats/output/charts/boomslang/PlotLayout.py
sofastats/output/charts/boomslang/Scatter.py
sofastats/output/charts/boomslang/StackedBars.py
sofastats/output/charts/boomslang/Utils.py
sofastats/output/charts/boomslang/__init__.py
sofastats/output/js/dojo.xd.js
sofastats/output/js/sofastats.js.uncompressed.js
sofastats/output/js/sofastats_charts.js
sofastats/output/stats/__init__.py
sofastats/output/stats/advice.html
sofastats_lib-0.12.3.dist-info/METADATA
sofastats_lib-0.12.3.dist-info/WHEEL
sofastats_lib-0.12.3.dist-info/licenses/LICENSE
sofastats_lib-0.12.3.dist-info/RECORD
