Metadata-Version: 2.4
Name: sofastats_lib
Version: 0.12.3
Summary: SOFA (Statistics Open For All) the Python library
Author-email: Grant Paton-Simpson <grant@sofastatistics.com>
License-File: LICENSE
Classifier: Development Status :: 1 - Planning
Requires-Python: >=3.11
Requires-Dist: beautifulsoup4>=4.12.3
Requires-Dist: jinja2>=3.1.3
Requires-Dist: matplotlib>=3.8.0
Requires-Dist: numpy>=1.26.4
Requires-Dist: pandas>=2
Requires-Dist: ruamel-yaml>=0.18.10
